torchvae/__init__.py
torchvae/lighting.py
torchvae/models.py
torchvae-0.1.0.dist-info/WHEEL
torchvae-0.1.0.dist-info/METADATA
torchvae-0.1.0.dist-info/RECORD
